{
  "timestamp": "2025-07-24T19:35:31.886Z",
  "installationId": "install-1753385731553",
  "healthScore": 100,
  "userExperience": {
    "satisfaction": 100,
    "speed": 100,
    "clarity": 100,
    "success": 100
  },
  "systemMetrics": {
    "diskSpace": 75608,
    "memoryAvailable": {
      "total": 4694016,
      "used": 4194640,
      "available": 499376,
      "adequate": true
    },
    "cpuLoad": 47.77165106936777,
    "networkSpeed": 119
  },
  "installationStrategy": {
    "approach": "standard",
    "priority": "user-experience",
    "timeline": 252.10084033613447,
    "resources": {
      "diskSpace": "2.5 GB",
      "memory": "512 MB",
      "bandwidth": "100 MB"
    },
    "riskMitigation": [
      "Automatic retry on failure",
      "Progressive fallback strategies",
      "Real-time error correction",
      "User guidance and support"
    ]
  },
  "issuesResolved": [],
  "optimizationsApplied": [],
  "installationLog": [],
  "preparationTime": 329
}